cvxpy_debug/__init__.py
cvxpy_debug/debug.py
cvxpy_debug/infeasibility/__init__.py
cvxpy_debug/infeasibility/diagnose.py
cvxpy_debug/infeasibility/elastic.py
cvxpy_debug/infeasibility/iis.py
cvxpy_debug/infeasibility/mapping.py
cvxpy_debug/infeasibility/relaxation.py
cvxpy_debug/infeasibility/solvers/__init__.py
cvxpy_debug/numerical/__init__.py
cvxpy_debug/numerical/conditioning.py
cvxpy_debug/numerical/dataclasses.py
cvxpy_debug/numerical/diagnose.py
cvxpy_debug/numerical/recommendations.py
cvxpy_debug/numerical/scaling.py
cvxpy_debug/numerical/solver_stats.py
cvxpy_debug/numerical/violations.py
cvxpy_debug/performance/__init__.py
cvxpy_debug/performance/dataclasses.py
cvxpy_debug/performance/diagnose.py
cvxpy_debug/performance/matrix_analysis.py
cvxpy_debug/performance/patterns.py
cvxpy_debug/performance/suggestions.py
cvxpy_debug/report/__init__.py
cvxpy_debug/report/report.py
cvxpy_debug/unbounded/__init__.py
cvxpy_debug/unbounded/bounds.py
cvxpy_debug/unbounded/diagnose.py
cvxpy_debug/unbounded/ray.py
cvxpy_debug/unbounded/suggestions.py
cvxpy_debug/utils/__init__.py
cvxpy_debug-0.1.0.dist-info/METADATA
cvxpy_debug-0.1.0.dist-info/WHEEL
cvxpy_debug-0.1.0.dist-info/licenses/LICENSE
cvxpy_debug-0.1.0.dist-info/RECORD
