Metadata-Version: 2.4
Name: cvxpy-debug
Version: 0.1.0
Summary: Diagnostic tools for CVXPY optimization problems
Project-URL: Homepage, https://github.com/SteveDiamond/cvxpy-debug
Project-URL: Repository, https://github.com/SteveDiamond/cvxpy-debug
Author: Steven Diamond
License-Expression: Apache-2.0
License-File: LICENSE
Keywords: convex,cvxpy,debugging,infeasibility,optimization
Classifier: Development Status :: 3 - Alpha
Classifier: Intended Audience :: Science/Research
Classifier: License :: OSI Approved :: Apache Software License
Classifier: Programming Language :: Python :: 3
Classifier: Programming Language :: Python :: 3.9
Classifier: Programming Language :: Python :: 3.10
Classifier: Programming Language :: Python :: 3.11
Classifier: Programming Language :: Python :: 3.12
Classifier: Topic :: Scientific/Engineering :: Mathematics
Requires-Python: >=3.9
Requires-Dist: cvxpy>=1.4
Requires-Dist: numpy
Provides-Extra: dev
Requires-Dist: pre-commit; extra == 'dev'
Requires-Dist: pyright; extra == 'dev'
Requires-Dist: pytest-cov; extra == 'dev'
Requires-Dist: pytest>=7.0; extra == 'dev'
Requires-Dist: ruff; extra == 'dev'
